salla_common_lib/__init__.py
salla_common_lib/utils.py
salla_common_lib/event/field_manager.py
salla_common_lib/event/item.py
salla_common_lib/event/item_price.py
salla_common_lib/event/salla_order.py
salla_common_lib/event/unified_integration.py
salla_common_lib-0.0.28.dist-info/WHEEL
salla_common_lib-0.0.28.dist-info/METADATA
salla_common_lib-0.0.28.dist-info/RECORD
