Metadata-Version: 2.4
Name: salla_common_lib
Version: 0.0.28
Summary: App for salla common lib
Author-email: Golive-Solutions <info@golive-solutions.com>
Requires-Python: >=3.10
